base/__init__.py
base/executors/__init__.py
base/executors/batch_work_executor.py
base/executors/bounded_executor.py
base/executors/fail_safe_executor.py
base/executors/utils/__init__.py
base/executors/utils/atomic_counter.py
base/executors/utils/progress_logger.py
base/executors/utils/retriable_value_error.py
base/executors/utils/utils.py
base/jobs/__init__.py
base/jobs/base_job.py
base/jobs/job_run_multithread.py
base/jobs/utils/__init__.py
base/jobs/utils/job_utils.py
base/mappers/__init__.py
base/mappers/eth_call_balance_of_mapper.py
base/mappers/eth_call_mapper.py
base/mappers/eth_json_rpc_mapper.py
base/mappers/get_balance_mapper.py
base/providers/__init__.py
base/providers/auto.py
base/providers/ipc.py
base/providers/rpc.py
base/utils/__init__.py
base/utils/decoder.py
base/utils/encoder.py
cli/__init__.py
cli/check_multithread.py
cli/check_telnet.py
cli/helper.py
cli/separate_host_port_multithread.py
cli/base/__init__.py
cli/base/executors/__init__.py
cli/base/executors/batch_work_executor.py
cli/base/executors/bounded_executor.py
cli/base/executors/fail_safe_executor.py
cli/base/executors/utils/__init__.py
cli/base/executors/utils/atomic_counter.py
cli/base/executors/utils/progress_logger.py
cli/base/executors/utils/retriable_value_error.py
cli/base/executors/utils/utils.py
cli/base/jobs/__init__.py
cli/base/jobs/base_job.py
cli/base/jobs/job_run_multithread.py
cli/base/jobs/utils/__init__.py
cli/base/jobs/utils/job_utils.py
cli/base/mappers/__init__.py
cli/base/mappers/eth_call_balance_of_mapper.py
cli/base/mappers/eth_call_mapper.py
cli/base/mappers/eth_json_rpc_mapper.py
cli/base/mappers/get_balance_mapper.py
cli/base/providers/__init__.py
cli/base/providers/auto.py
cli/base/providers/ipc.py
cli/base/providers/rpc.py
cli/base/utils/__init__.py
cli/base/utils/decoder.py
cli/base/utils/encoder.py
Help_Tool_ThanhNv-1.1.4.dist-info/LICENSE
Help_Tool_ThanhNv-1.1.4.dist-info/METADATA
Help_Tool_ThanhNv-1.1.4.dist-info/WHEEL
Help_Tool_ThanhNv-1.1.4.dist-info/entry_points.txt
Help_Tool_ThanhNv-1.1.4.dist-info/top_level.txt
Help_Tool_ThanhNv-1.1.4.dist-info/RECORD
