Metadata-Version: 2.1
Name: Help-Tool-ThanhNv
Version: 1.1.4
Home-page: https://github.com/thanhnv2303/HelpTool
Author: LinLin
Author-email: nguyenthanh2303@gmail.com
Project-URL: Bug Tracker, https://github.com/thanhnv2303/HelpTool
Keywords: checkport
Classifier: Development Status :: 5 - Production/Stable
Classifier: Intended Audience :: Developers
Classifier: License :: OSI Approved :: MIT License
Classifier: Programming Language :: Python :: 3
Classifier: Programming Language :: Python :: 3.7
Classifier: Programming Language :: Python :: 3.8
Classifier: Programming Language :: Python :: 3.9
Requires-Python: >=3.7.2,<4
License-File: LICENSE
Requires-Dist: requests <=2.26.0
Requires-Dist: click <9,>=8.0.4
Requires-Dist: sortedcontainers ==2.4.0
